kozh_fig_pac2
