Metadata-Version: 2.1
Name: kozh-fig-pac2
Version: 0.2
Summary: circle, tiangle, square
Author-email: alexeykozhakin@gmail.com
